voluxlight/__init__.py
voluxlight/__init___WIP.py
voluxlight/__version__.py
voluxlight-2.0.1.dist-info/METADATA
voluxlight-2.0.1.dist-info/WHEEL
voluxlight-2.0.1.dist-info/RECORD
